llama_index/llms/palm/__init__.py
llama_index/llms/palm/base.py
llama_index_llms_palm-0.4.1.dist-info/METADATA
llama_index_llms_palm-0.4.1.dist-info/WHEEL
llama_index_llms_palm-0.4.1.dist-info/licenses/LICENSE
llama_index_llms_palm-0.4.1.dist-info/RECORD
