Metadata-Version: 2.4
Name: llama-index-llms-palm
Version: 0.4.1
Summary: llama-index llms palm integration
Author-email: Your Name <you@example.com>
License-Expression: MIT
License-File: LICENSE
Requires-Python: <4.0,>=3.9
Requires-Dist: google-generativeai<0.6,>=0.5.2
Requires-Dist: llama-index-core<0.15,>=0.13.0
